cb_jtag/__init__.py
cb_jtag/cb_bit.py
cb_jtag/cb_bsr.py
cb_jtag/cb_jlink.py
cb_jtag/cb_jtag.py
cb_jtag/cb_jtag_fsm.py
cb_jtag/cb_jtag_iface_base.py
cb_jtag_examples/cb_jtag_ex0__nucleo-G474RE.py
cb_jtag_examples/cb_jtag_ex0__nucleo-U575ZI-Q.py
cb_jtag-0.2.0.dist-info/METADATA
cb_jtag-0.2.0.dist-info/WHEEL
cb_jtag-0.2.0.dist-info/RECORD
